{
"meta":{"test_sets":[],"test_metrics":[],"learn_metrics":[{"best_value":"Min","name":"Logloss"}],"launch_mode":"Train","parameters":"","iteration_count":100,"learn_sets":["learn"],"name":"experiment"},
"iterations":[
{"learn":[0.657575955],"iteration":0,"passed_time":0.03419215512,"remaining_time":3.385023357},
{"learn":[0.6267277471],"iteration":1,"passed_time":0.05805012775,"remaining_time":2.84445626},
{"learn":[0.6009749218],"iteration":2,"passed_time":0.08059437283,"remaining_time":2.605884722},
{"learn":[0.5800664744],"iteration":3,"passed_time":0.1075416017,"remaining_time":2.58099844},
{"learn":[0.562202577],"iteration":4,"passed_time":0.134372771,"remaining_time":2.55308265},
{"learn":[0.5468756886],"iteration":5,"passed_time":0.1626188842,"remaining_time":2.547695852},
{"learn":[0.5350440872],"iteration":6,"passed_time":0.1891061873,"remaining_time":2.512410774},
{"learn":[0.5234633951],"iteration":7,"passed_time":0.2164478693,"remaining_time":2.489150497},
{"learn":[0.5142501115],"iteration":8,"passed_time":0.2428134266,"remaining_time":2.455113536},
{"learn":[0.5047558259],"iteration":9,"passed_time":0.2699311241,"remaining_time":2.429380117},
{"learn":[0.4971984032],"iteration":10,"passed_time":0.2964895865,"remaining_time":2.398870291},
{"learn":[0.4885866951],"iteration":11,"passed_time":0.3240401629,"remaining_time":2.376294528},
{"learn":[0.4810308328],"iteration":12,"passed_time":0.3562802771,"remaining_time":2.384337239},
{"learn":[0.4747815357],"iteration":13,"passed_time":0.381371863,"remaining_time":2.342712873},
{"learn":[0.4678529219],"iteration":14,"passed_time":0.4075728617,"remaining_time":2.30957955},
{"learn":[0.4621404008],"iteration":15,"passed_time":0.4343671446,"remaining_time":2.280427509},
{"learn":[0.457176613],"iteration":16,"passed_time":0.4725730897,"remaining_time":2.307268615},
{"learn":[0.4528271145],"iteration":17,"passed_time":0.494230425,"remaining_time":2.251494158},
{"learn":[0.4487323967],"iteration":18,"passed_time":0.5197013331,"remaining_time":2.215568841},
{"learn":[0.4459259772],"iteration":19,"passed_time":0.5453404915,"remaining_time":2.181361966},
{"learn":[0.4418719179],"iteration":20,"passed_time":0.5708996739,"remaining_time":2.147670202},
{"learn":[0.4385739429],"iteration":21,"passed_time":0.5975957639,"remaining_time":2.118748617},
{"learn":[0.4352125878],"iteration":22,"passed_time":0.6378204433,"remaining_time":2.135311919},
{"learn":[0.4324192874],"iteration":23,"passed_time":0.6624092301,"remaining_time":2.097629229},
{"learn":[0.4296843783],"iteration":24,"passed_time":0.6880458394,"remaining_time":2.064137518},
{"learn":[0.4276789631],"iteration":25,"passed_time":0.7120656491,"remaining_time":2.026648386},
{"learn":[0.4260294025],"iteration":26,"passed_time":0.7366896725,"remaining_time":1.991790596},
{"learn":[0.4244193047],"iteration":27,"passed_time":0.7617823781,"remaining_time":1.958868972},
{"learn":[0.4227112213],"iteration":28,"passed_time":0.7871906104,"remaining_time":1.92725977},
{"learn":[0.4207904532],"iteration":29,"passed_time":0.8111850414,"remaining_time":1.892765097},
{"learn":[0.4203278317],"iteration":30,"passed_time":0.8284443596,"remaining_time":1.8439568},
{"learn":[0.4192873591],"iteration":31,"passed_time":0.8559224422,"remaining_time":1.81883519},
{"learn":[0.4184907505],"iteration":32,"passed_time":0.8814078869,"remaining_time":1.789525104},
{"learn":[0.4182374004],"iteration":33,"passed_time":0.89050645,"remaining_time":1.728630168},
{"learn":[0.4172951051],"iteration":34,"passed_time":0.9162415218,"remaining_time":1.701591398},
{"learn":[0.41644512],"iteration":35,"passed_time":0.9404740828,"remaining_time":1.671953925},
{"learn":[0.4151897078],"iteration":36,"passed_time":0.9640601658,"remaining_time":1.64150785},
{"learn":[0.4138233026],"iteration":37,"passed_time":0.98916017,"remaining_time":1.613892909},
{"learn":[0.4133592518],"iteration":38,"passed_time":1.015856804,"remaining_time":1.588904232},
{"learn":[0.4123704878],"iteration":39,"passed_time":1.046735249,"remaining_time":1.570102874},
{"learn":[0.4114562539],"iteration":40,"passed_time":1.072416848,"remaining_time":1.543234001},
{"learn":[0.410795156],"iteration":41,"passed_time":1.099864114,"remaining_time":1.518859967},
{"learn":[0.4101633002],"iteration":42,"passed_time":1.136602945,"remaining_time":1.506659718},
{"learn":[0.4097607865],"iteration":43,"passed_time":1.16369244,"remaining_time":1.481063105},
{"learn":[0.4088006148],"iteration":44,"passed_time":1.209941159,"remaining_time":1.478816972},
{"learn":[0.4081973138],"iteration":45,"passed_time":1.236629578,"remaining_time":1.451695591},
{"learn":[0.4077974203],"iteration":46,"passed_time":1.275337135,"remaining_time":1.438146131},
{"learn":[0.4075533276],"iteration":47,"passed_time":1.301879328,"remaining_time":1.410369272},
{"learn":[0.4072560163],"iteration":48,"passed_time":1.3309329,"remaining_time":1.385256692},
{"learn":[0.4064670559],"iteration":49,"passed_time":1.358345014,"remaining_time":1.358345014},
{"learn":[0.4061149676],"iteration":50,"passed_time":1.386155059,"remaining_time":1.331796037},
{"learn":[0.404873877],"iteration":51,"passed_time":1.411168075,"remaining_time":1.302616684},
{"learn":[0.4043797908],"iteration":52,"passed_time":1.436656086,"remaining_time":1.274015774},
{"learn":[0.4041078453],"iteration":53,"passed_time":1.464102923,"remaining_time":1.247198786},
{"learn":[0.4038399663],"iteration":54,"passed_time":1.489385666,"remaining_time":1.218588272},
{"learn":[0.4035237344],"iteration":55,"passed_time":1.513986458,"remaining_time":1.189560788},
{"learn":[0.402470309],"iteration":56,"passed_time":1.537861337,"remaining_time":1.160141009},
{"learn":[0.4022494577],"iteration":57,"passed_time":1.561778017,"remaining_time":1.130942702},
{"learn":[0.402139782],"iteration":58,"passed_time":1.587261372,"remaining_time":1.10301214},
{"learn":[0.4018310359],"iteration":59,"passed_time":1.612255425,"remaining_time":1.07483695},
{"learn":[0.4016359869],"iteration":60,"passed_time":1.637288612,"remaining_time":1.04679108},
{"learn":[0.4015739507],"iteration":61,"passed_time":1.657311268,"remaining_time":1.015771422},
{"learn":[0.4009576637],"iteration":62,"passed_time":1.683412449,"remaining_time":0.9886708034},
{"learn":[0.4004279691],"iteration":63,"passed_time":1.708206438,"remaining_time":0.9608661211},
{"learn":[0.3996099978],"iteration":64,"passed_time":1.733980039,"remaining_time":0.9336815594},
{"learn":[0.3992730159],"iteration":65,"passed_time":1.759078751,"remaining_time":0.9061920841},
{"learn":[0.3991023482],"iteration":66,"passed_time":1.786622181,"remaining_time":0.8799780891},
{"learn":[0.3989061739],"iteration":67,"passed_time":1.812729381,"remaining_time":0.8530491203},
{"learn":[0.3988465299],"iteration":68,"passed_time":1.838078914,"remaining_time":0.8258035699},
{"learn":[0.3986619402],"iteration":69,"passed_time":1.86376928,"remaining_time":0.798758263},
{"learn":[0.3986005356],"iteration":70,"passed_time":1.882430703,"remaining_time":0.7688801463},
{"learn":[0.3981788193],"iteration":71,"passed_time":1.908189121,"remaining_time":0.7420735471},
{"learn":[0.3981043665],"iteration":72,"passed_time":1.933972748,"remaining_time":0.7153049891},
{"learn":[0.3980638288],"iteration":73,"passed_time":1.951306632,"remaining_time":0.685594222},
{"learn":[0.3980570858],"iteration":74,"passed_time":1.977005904,"remaining_time":0.6590019679},
{"learn":[0.3977452837],"iteration":75,"passed_time":2.002617267,"remaining_time":0.6324054528},
{"learn":[0.3974623465],"iteration":76,"passed_time":2.028408572,"remaining_time":0.6058882746},
{"learn":[0.3973731445],"iteration":77,"passed_time":2.047990559,"remaining_time":0.5776383628},
{"learn":[0.39737249],"iteration":78,"passed_time":2.057516996,"remaining_time":0.5469348977},
{"learn":[0.3973072155],"iteration":79,"passed_time":2.083564431,"remaining_time":0.5208911076},
{"learn":[0.3971665227],"iteration":80,"passed_time":2.110952796,"remaining_time":0.4951617669},
{"learn":[0.3971559367],"iteration":81,"passed_time":2.132880298,"remaining_time":0.4681932361},
{"learn":[0.3968916509],"iteration":82,"passed_time":2.160255883,"remaining_time":0.4424620484},
{"learn":[0.396673185],"iteration":83,"passed_time":2.18700691,"remaining_time":0.4165727448},
{"learn":[0.3965537294],"iteration":84,"passed_time":2.214476023,"remaining_time":0.3907898865},
{"learn":[0.3963147797],"iteration":85,"passed_time":2.241493488,"remaining_time":0.3648942888},
{"learn":[0.3960791202],"iteration":86,"passed_time":2.269919824,"remaining_time":0.339183422},
{"learn":[0.3958755405],"iteration":87,"passed_time":2.298742601,"remaining_time":0.3134649001},
{"learn":[0.3957055741],"iteration":88,"passed_time":2.326928094,"remaining_time":0.2875978543},
{"learn":[0.3947104222],"iteration":89,"passed_time":2.352260294,"remaining_time":0.2613622548},
{"learn":[0.39450233],"iteration":90,"passed_time":2.376789507,"remaining_time":0.2350670941},
{"learn":[0.3944093856],"iteration":91,"passed_time":2.400246706,"remaining_time":0.2087171048},
{"learn":[0.3941919653],"iteration":92,"passed_time":2.424119845,"remaining_time":0.1824606335},
{"learn":[0.3940815772],"iteration":93,"passed_time":2.448846753,"remaining_time":0.1563093672},
{"learn":[0.3940120945],"iteration":94,"passed_time":2.472440831,"remaining_time":0.1301284648},
{"learn":[0.3938036419],"iteration":95,"passed_time":2.496560082,"remaining_time":0.1040233367},
{"learn":[0.3937067459],"iteration":96,"passed_time":2.519461213,"remaining_time":0.0779214808},
{"learn":[0.3935226856],"iteration":97,"passed_time":2.54559023,"remaining_time":0.05195082103},
{"learn":[0.3932527843],"iteration":98,"passed_time":2.570165079,"remaining_time":0.02596126342},
{"learn":[0.3924381022],"iteration":99,"passed_time":2.596653661,"remaining_time":0}
]}